[{"Year":1970,"Value":0.45277},{"Year":1971,"Value":0.40823},{"Year":1972,"Value":0.65772},{"Year":1973,"Value":0.4998},{"Year":1974,"Value":0.62223},{"Year":1975,"Value":0.40499},{"Year":1976,"Value":0.28493},{"Year":1977,"Value":0.41118},{"Year":1978,"Value":0.49776},{"Year":1979,"Value":0.30701},{"Year":1980,"Value":0.38154},{"Year":1981,"Value":1.14582},{"Year":1982,"Value":1.05697},{"Year":1983,"Value":0.97137},{"Year":1984,"Value":0.91675},{"Year":1985,"Value":1.07579},{"Year":1986,"Value":0.72025},{"Year":1987,"Value":0.82802},{"Year":1988,"Value":0.9163},{"Year":1989,"Value":1.07568},{"Year":1990,"Value":1.62452},{"Year":1991,"Value":1.52218},{"Year":1992,"Value":1.39893},{"Year":1993,"Value":2.05397},{"Year":1994,"Value":1.9205},{"Year":1995,"Value":0.96722},{"Year":1996,"Value":0.72675},{"Year":1997,"Value":3.86264},{"Year":1998,"Value":3.77404},{"Year":1999,"Value":4.53516},{"Year":2000,"Value":4.23365},{"Year":2001,"Value":0.39207},{"Year":2002,"Value":0.43463},{"Year":2003,"Value":0.44178},{"Year":2004,"Value":2.33491},{"Year":2005,"Value":2.26808},{"Year":2006,"Value":2.2089},{"Year":2007,"Value":2.01894},{"Year":2008,"Value":1.85906},{"Year":2009,"Value":1.49117},{"Year":2010,"Value":1.51029},{"Year":2011,"Value":1.99307},{"Year":2012,"Value":2.14732},{"Year":2013,"Value":2.11487},{"Year":2014,"Value":2.11002},{"Year":2015,"Value":2.23795},{"Year":2016,"Value":2.33194},{"Year":2017,"Value":2.39196},{"Year":2018,"Value":2.95041},{"Year":2019,"Value":2.82251},{"Year":2020,"Value":3.06889}]